DatasetsHelperQ/__init__.py
DatasetsHelperQ/image.py
DatasetsHelperQ/mapping.py
DatasetsHelperQ/normalization.py
DatasetsHelperQ/data/mapping.json
DatasetsHelper-0.0.3.dist-info/LICENSE
DatasetsHelper-0.0.3.dist-info/METADATA
DatasetsHelper-0.0.3.dist-info/WHEEL
DatasetsHelper-0.0.3.dist-info/top_level.txt
DatasetsHelper-0.0.3.dist-info/RECORD
